nendo_plugin_stemify_demucs/__init__.py
nendo_plugin_stemify_demucs/config.py
nendo_plugin_stemify_demucs/plugin.py
nendo_plugin_stemify_demucs/utils.py
nendo_plugin_stemify_demucs-0.1.3.dist-info/LICENSE
nendo_plugin_stemify_demucs-0.1.3.dist-info/METADATA
nendo_plugin_stemify_demucs-0.1.3.dist-info/WHEEL
nendo_plugin_stemify_demucs-0.1.3.dist-info/RECORD
