Metadata-Version: 2.1
Name: nendo-plugin-stemify-demucs
Version: 0.1.3
Summary: Nendo Plugin for Music Source Separation.
Home-page: https://okio.ai
License: MIT
Keywords: Nendo,AI,Machine Learning,Audio,Generative,Music,Audio Production,Audio Generation,Audio Analysis,Stemification,Souce Separation
Author: Aaron Abebe
Author-email: aaron@okio.ai
Requires-Python: >=3.8,<3.11
Classifier: Development Status :: 5 - Production/Stable
Classifier: Environment :: Console
Classifier: Intended Audience :: Developers
Classifier: License :: OSI Approved :: MIT License
Classifier: Operating System :: OS Independent
Classifier: Programming Language :: Python :: 3
Classifier: Programming Language :: Python :: 3.8
Classifier: Programming Language :: Python :: 3.9
Classifier: Programming Language :: Python :: 3.10
Requires-Dist: demucs (>=4.0.1,<5.0.0)
Requires-Dist: nendo (>=0.2.0,<0.3.0)
Requires-Dist: pydantic (>=2.0.0,<2.5.0)
Requires-Dist: pydantic-settings (>=2.1.0,<3.0.0)
Project-URL: Repository, https://github.com/okio-ai/nendo_plugin_stemify_demucs
